flask_pika.py
setup.py
Flask_Pika.egg-info/PKG-INFO
Flask_Pika.egg-info/SOURCES.txt
Flask_Pika.egg-info/dependency_links.txt
Flask_Pika.egg-info/not-zip-safe
Flask_Pika.egg-info/requires.txt
Flask_Pika.egg-info/top_level.txt