Metadata-Version: 1.1
Name: Flask-Pika
Version: 0.3.8
Summary: Pika amqp flask extension
Home-page: https://github.com/WeatherDecisionTechnologies/flask-pika
Author: Weather Decision Technologies
Author-email: alertingdevelopers@wdtinc.com
License: BSD
Platform: any
Classifier: Environment :: Web Environment
Classifier: Intended Audience :: Developers
Classifier: Operating System :: OS Independent
Classifier: Programming Language :: Python
Classifier: Topic :: Internet :: WWW/HTTP :: Dynamic Content
Classifier: Topic :: Software Development :: Libraries :: Python Modules
